_hydrogenlib_resource_system/__about__.py
_hydrogenlib_resource_system/__init__.py
_hydrogenlib_resource_system/builtin_providers.py
_hydrogenlib_resource_system/system.py
_hydrogenlib_resource_system/utils.py
_hydrogenlib_resource_system/core/__init__.py
_hydrogenlib_resource_system/core/errors.py
_hydrogenlib_resource_system/core/provider.py
_hydrogenlib_resource_system/core/system.py
_hydrogenlib_resource_system/core/url/__init__.py
_hydrogenlib_resource_system/core/url/url.py
hydrogenlib_resource_system-0.3.0.dist-info/METADATA
hydrogenlib_resource_system-0.3.0.dist-info/WHEEL
hydrogenlib_resource_system-0.3.0.dist-info/RECORD
